zutilities/__init__.py
zutilities/logger.py
zutilities/zutilities.py
zutilities-0.1.2.dist-info/LICENSE
zutilities-0.1.2.dist-info/METADATA
zutilities-0.1.2.dist-info/WHEEL
zutilities-0.1.2.dist-info/top_level.txt
zutilities-0.1.2.dist-info/RECORD
